qinternal/__init__.py
qinternal/core/__init__.py
qinternal/core/byte_units.py
qumulo/__init__.py
qumulo/rest_client.py
qumulo/retry.py
qumulo/commands/__init__.py
qumulo/commands/access_tokens.py
qumulo/commands/ad.py
qumulo/commands/analytics.py
qumulo/commands/audit.py
qumulo/commands/auth.py
qumulo/commands/authoritative_dns.py
qumulo/commands/capacity.py
qumulo/commands/checksumming.py
qumulo/commands/cluster.py
qumulo/commands/dns.py
qumulo/commands/encryption.py
qumulo/commands/file_permissions_help.py
qumulo/commands/fs.py
qumulo/commands/ftp.py
qumulo/commands/kerberos.py
qumulo/commands/key_store.py
qumulo/commands/ldap.py
qumulo/commands/login.py
qumulo/commands/metrics.py
qumulo/commands/multitenancy.py
qumulo/commands/multitenancy_nfs.py
qumulo/commands/multitenancy_smb.py
qumulo/commands/network.py
qumulo/commands/network_v3.py
qumulo/commands/nexus.py
qumulo/commands/nfs.py
qumulo/commands/node_state.py
qumulo/commands/object_replication.py
qumulo/commands/object_storage.py
qumulo/commands/portal.py
qumulo/commands/quota.py
qumulo/commands/raw.py
qumulo/commands/replication.py
qumulo/commands/roles.py
qumulo/commands/s3.py
qumulo/commands/saml.py
qumulo/commands/shutdown.py
qumulo/commands/smb.py
qumulo/commands/snapshot.py
qumulo/commands/software_license.py
qumulo/commands/support.py
qumulo/commands/time_config.py
qumulo/commands/tree_delete.py
qumulo/commands/unconfigured_node_operations.py
qumulo/commands/upgrade.py
qumulo/commands/version.py
qumulo/commands/web_ui.py
qumulo/lib/__init__.py
qumulo/lib/acl_util.py
qumulo/lib/auth.py
qumulo/lib/duration.py
qumulo/lib/identity_util.py
qumulo/lib/keys.py
qumulo/lib/obj.py
qumulo/lib/opts.py
qumulo/lib/qq.py
qumulo/lib/request.py
qumulo/lib/rest_util.py
qumulo/lib/rfc3339.py
qumulo/lib/tenant.py
qumulo/lib/uri.py
qumulo/lib/util.py
qumulo/rest/__init__.py
qumulo/rest/access_tokens.py
qumulo/rest/ad.py
qumulo/rest/analytics.py
qumulo/rest/audit.py
qumulo/rest/auth.py
qumulo/rest/authoritative_dns.py
qumulo_api-7.7.4.dist-info/LICENSE
qumulo_api-7.7.4.dist-info/METADATA
qumulo_api-7.7.4.dist-info/NOTICE
qumulo_api-7.7.4.dist-info/WHEEL
qumulo_api-7.7.4.dist-info/entry_points.txt
qumulo_api-7.7.4.dist-info/top_level.txt
qumulo_api-7.7.4.dist-info/RECORD
