Metadata-Version: 2.1
Name: qumulo-api
Version: 7.7.4
Summary: Qumulo Python SDK
Home-page: http://www.qumulo.com/
Author: Qumulo, Inc.
Author-email: python@qumulo.com
License: UNKNOWN
Keywords: Qumulo QFSD
Platform: UNKNOWN
Classifier: Operating System :: OS Independent
Classifier: Programming Language :: Python :: 3
Classifier: Programming Language :: Python :: 3.8
Requires-Python: >=3.8, <4
License-File: LICENSE
License-File: NOTICE
Requires-Dist: dataclasses-json (>=0.5.2)
Requires-Dist: python-dateutil (>=2.8.2)
Requires-Dist: tqdm (>=4.24.0)
Requires-Dist: typing-extensions (>=3.7.4.3)
